exonware/xentity/__init__.py
exonware_xentity-0.0.1.dist-info/METADATA
exonware_xentity-0.0.1.dist-info/WHEEL
exonware_xentity-0.0.1.dist-info/licenses/LICENSE
exonware_xentity-0.0.1.dist-info/RECORD
